butterneck_projen/__init__.py
butterneck_projen/py.typed
butterneck_projen/_jsii/__init__.py
butterneck_projen/_jsii/butterneck-projen@0.0.9.jsii.tgz
butterneck_projen-0.0.9.dist-info/LICENSE
butterneck_projen-0.0.9.dist-info/METADATA
butterneck_projen-0.0.9.dist-info/WHEEL
butterneck_projen-0.0.9.dist-info/top_level.txt
butterneck_projen-0.0.9.dist-info/RECORD
