Metadata-Version: 2.1
Name: butterneck-projen
Version: 0.0.9
Summary: butterneck-projen
Home-page: https://github.com/butterneck/butterneck-projen.git
Author: Filippo Pinton<pinton.filippo@protonmail.com>
License: Apache-2.0
Project-URL: Source, https://github.com/butterneck/butterneck-projen.git
Classifier: Intended Audience :: Developers
Classifier: Operating System :: OS Independent
Classifier: Programming Language :: JavaScript
Classifier: Programming Language :: Python :: 3 :: Only
Classifier: Programming Language :: Python :: 3.7
Classifier: Programming Language :: Python :: 3.8
Classifier: Programming Language :: Python :: 3.9
Classifier: Programming Language :: Python :: 3.10
Classifier: Programming Language :: Python :: 3.11
Classifier: Typing :: Typed
Classifier: Development Status :: 5 - Production/Stable
Classifier: License :: OSI Approved
Requires-Python: ~=3.7
License-File: LICENSE
Requires-Dist: jsii (<2.0.0,>=1.80.0)
Requires-Dist: projen (<0.72.0,>=0.71.0)
Requires-Dist: publication (>=0.0.3)
Requires-Dist: typeguard (~=2.13.3)
